RawRefinery/__init__.py
RawRefinery/main.py
RawRefinery/application/ClickableImageLabel.py
RawRefinery/application/LogarithmicSlider.py
RawRefinery/application/ModelHandler.py
RawRefinery/application/RawRefineryApp.py
RawRefinery/application/dng_utils.py
RawRefinery/application/postprocessing.py
RawRefinery/application/utils.py
RawRefinery/application/viewing_utils.py
rawrefinery-1.3.4.dist-info/licenses/LICENSE
rawrefinery-1.3.4.dist-info/METADATA
rawrefinery-1.3.4.dist-info/WHEEL
rawrefinery-1.3.4.dist-info/entry_points.txt
rawrefinery-1.3.4.dist-info/top_level.txt
rawrefinery-1.3.4.dist-info/RECORD
