Metadata-Version: 2.4
Name: rawrefinery
Version: 1.3.4
Summary: A demosaicing, denoising, and refining application for raw images.
Author: Ryan Mueller
License: MIT License
Project-URL: Homepage, https://github.com/rymuelle/RawRefinery
Project-URL: Bug Tracker, https://github.com/rymuelle/RawRefinery/issues
Keywords: python,Machine Learning,Camera Raw
Classifier: Programming Language :: Python :: 3
Classifier: Programming Language :: Python :: 3.11
Classifier: Programming Language :: Python :: 3.12
Classifier: Programming Language :: Python :: 3.13
Classifier: License :: OSI Approved :: MIT License
Classifier: Operating System :: OS Independent
Requires-Python: >=3.11
License-File: LICENSE
Requires-Dist: pidng~=4.0.9
Requires-Dist: pyside6~=6.9
Requires-Dist: numpy>=2.3
Requires-Dist: RawHandler~=0.0.2
Requires-Dist: colour_demosaicing~=0.2.6
Requires-Dist: blended_tiling>=0.0.1.dev7
Requires-Dist: requests~=2.32
Requires-Dist: platformdirs~=4.5
Requires-Dist: tqdm~=4.67
Requires-Dist: cryptography~=46.0
Provides-Extra: torch-legacy
Requires-Dist: torch~=2.2; extra == "torch-legacy"
Provides-Extra: torch-tested
Requires-Dist: torch~=2.8; extra == "torch-tested"
Dynamic: license-file
